plone.app.blob-1.8.1-py2.7-nspkg.pth
plone/app/blob/README.txt
plone/app/blob/__init__.py
plone/app/blob/config.py
plone/app/blob/configure.zcml
plone/app/blob/content.py
plone/app/blob/download.py
plone/app/blob/field.py
plone/app/blob/interfaces.py
plone/app/blob/iterators.py
plone/app/blob/markings.py
plone/app/blob/migrations.py
plone/app/blob/mixins.py
plone/app/blob/monkey.py
plone/app/blob/profiles.zcml
plone/app/blob/scale.py
plone/app/blob/testing3rdparty.txt
plone/app/blob/utils.py
plone/app/blob/adapters/__init__.py
plone/app/blob/adapters/atfile.py
plone/app/blob/adapters/atimage.py
plone/app/blob/adapters/blobwrapper.py
plone/app/blob/adapters/configure.zcml
plone/app/blob/adapters/file.py
plone/app/blob/adapters/fileupload.py
plone/app/blob/adapters/ofsfile.py
plone/app/blob/adapters/pdata.py
plone/app/blob/adapters/stringio.py
plone/app/blob/adapters/webdav.py
plone/app/blob/adapters/xmlrpc.py
plone/app/blob/browser/__init__.py
plone/app/blob/browser/configure.zcml
plone/app/blob/browser/maintenance.py
plone/app/blob/browser/migration.pt
plone/app/blob/browser/migration.py
plone/app/blob/browser/size.py
plone/app/blob/profiles/default/metadata.xml
plone/app/blob/profiles/file-replacement/factorytool.xml
plone/app/blob/profiles/file-replacement/metadata.xml
plone/app/blob/profiles/file-replacement/types.xml
plone/app/blob/profiles/file-replacement/workflows.xml
plone/app/blob/profiles/file-replacement/types/ATFile.xml
plone/app/blob/profiles/file-replacement/types/File.xml
plone/app/blob/profiles/image-replacement/factorytool.xml
plone/app/blob/profiles/image-replacement/metadata.xml
plone/app/blob/profiles/image-replacement/types.xml
plone/app/blob/profiles/image-replacement/workflows.xml
plone/app/blob/profiles/image-replacement/types/ATImage.xml
plone/app/blob/profiles/image-replacement/types/Image.xml
plone/app/blob/profiles/lingua/factorytool.xml
plone/app/blob/profiles/lingua/metadata.xml
plone/app/blob/profiles/lingua/rolemap.xml
plone.app.blob-1.8.1.dist-info/METADATA
plone.app.blob-1.8.1.dist-info/WHEEL
plone.app.blob-1.8.1.dist-info/entry_points.txt
plone.app.blob-1.8.1.dist-info/namespace_packages.txt
plone.app.blob-1.8.1.dist-info/top_level.txt
plone.app.blob-1.8.1.dist-info/RECORD
