Metadata-Version: 2.1
Name: plone.app.blob
Version: 1.8.1
Summary: ZODB blob support for Plone
Home-page: http://plone.org/products/plone.app.blob
Author: Plone Foundation
Author-email: plone-developers@lists.sourceforge.net
License: GPL version 2
Download-URL: https://pypi.org/project/plone.app.blob/
Keywords: zodb blob support plone integration
Platform: Any
Classifier: Development Status :: 6 - Mature
Classifier: Environment :: Web Environment
Classifier: Framework :: Plone :: 5.2
Classifier: Framework :: Plone
Classifier: Framework :: Zope
Classifier: Framework :: Zope :: 4
Classifier: Intended Audience :: Developers
Classifier: Intended Audience :: Other Audience
Classifier: Intended Audience :: System Administrators
Classifier: License :: OSI Approved :: GNU General Public License v2 (GPLv2)
Classifier: Operating System :: OS Independent
Classifier: Programming Language :: Python :: 2.7
Classifier: Programming Language :: Python
Requires-Dist: Products.CMFPlone
Requires-Dist: Products.MimetypesRegistry
Requires-Dist: ZODB3 (>=3.8.1)
Requires-Dist: archetypes.schemaextender (>=1.6)
Requires-Dist: plone.app.imaging (>1.0b9)
Requires-Dist: plone.scale
Requires-Dist: setuptools
Requires-Dist: six
Requires-Dist: zope.proxy (>=3.4)
Provides-Extra: test
Requires-Dist: Products.contentmigration ; extra == 'test'
Requires-Dist: collective.monkeypatcher ; extra == 'test'
Requires-Dist: plone.app.imaging ; extra == 'test'
Requires-Dist: plone.app.testing ; extra == 'test'
